immich/.openapi-generator/FILES
immich/.openapi-generator/VERSION
immich/__init__.py
immich/cli/__main__.py
immich/cli/commands/activities.py
immich/cli/commands/albums.py
immich/cli/commands/api_keys.py
immich/cli/commands/assets.py
immich/cli/commands/authentication.py
immich/cli/commands/authentication_admin.py
immich/cli/commands/database_backups_admin.py
immich/cli/commands/download.py
immich/cli/commands/duplicates.py
immich/cli/commands/faces.py
immich/cli/commands/jobs.py
immich/cli/commands/libraries.py
immich/cli/commands/maintenance_admin.py
immich/cli/commands/map.py
immich/cli/commands/memories.py
immich/cli/commands/notifications.py
immich/cli/commands/notifications_admin.py
immich/cli/commands/partners.py
immich/cli/commands/people.py
immich/cli/commands/plugins.py
immich/cli/commands/queues.py
immich/cli/commands/search.py
immich/cli/commands/server.py
immich/cli/commands/sessions.py
immich/cli/commands/shared_links.py
immich/cli/commands/stacks.py
immich/cli/commands/sync.py
immich/cli/commands/system_config.py
immich/cli/commands/system_metadata.py
immich/cli/commands/tags.py
immich/cli/commands/timeline.py
immich/cli/commands/trash.py
immich/cli/commands/users.py
immich/cli/commands/users_admin.py
immich/cli/commands/views.py
immich/cli/commands/workflows.py
immich/cli/consts.py
immich/cli/main.py
immich/cli/runtime.py
immich/cli/types.py
immich/cli/utils.py
immich/cli/wrapper/assets.py
immich/cli/wrapper/config.py
immich/cli/wrapper/download.py
immich/cli/wrapper/setup.py
immich/cli/wrapper/users.py
immich/client/.openapi-generator/FILES
immich/client/.openapi-generator/VERSION
immich/client/.openapi-generator-ignore
immich/client/__init__.py
immich/client/consts.py
immich/client/generated/__init__.py
immich/client/generated/api/__init__.py
immich/client/generated/api/activities_api.py
immich/client/generated/api/albums_api.py
immich/client/generated/api/api_keys_api.py
immich/client/generated/api/assets_api.py
immich-1.7.4.dist-info/licenses/LICENSE
immich-1.7.4.dist-info/WHEEL
immich-1.7.4.dist-info/entry_points.txt
immich-1.7.4.dist-info/METADATA
immich-1.7.4.dist-info/RECORD
